torob_integration/__init__.py
torob_integration/api.py
torob_integration-0.0.2.dist-info/LICENSE
torob_integration-0.0.2.dist-info/METADATA
torob_integration-0.0.2.dist-info/WHEEL
torob_integration-0.0.2.dist-info/top_level.txt
torob_integration-0.0.2.dist-info/RECORD
