Metadata-Version: 2.1
Name: torob-integration
Version: 0.0.2
Summary: A Python module facilitating effortless interaction with the Torob API for seamless access to product data.
Home-page: https://github.com/hamidrezafarzin/Torob-Integration
Author: Hamidreza Farzin
Author-email: hamidfarzin1382@gmail.com
Project-URL: Author, https://github.com/hamidrezafarzin
Classifier: Programming Language :: Python :: 3
Classifier: License :: OSI Approved :: MIT License
Classifier: Operating System :: OS Independent
Requires-Python: >=3.6
License-File: LICENSE
Requires-Dist: requests
